uml2img/__init__.py
uml2img/cli.py
uml2img/core.py
uml2img/plantuml.jar
uml2img-0.1.0.dist-info/METADATA
uml2img-0.1.0.dist-info/WHEEL
uml2img-0.1.0.dist-info/entry_points.txt
uml2img-0.1.0.dist-info/top_level.txt
uml2img-0.1.0.dist-info/RECORD
